subtitle_corrector/__init__.py
subtitle_corrector/config.json
subtitle_corrector/error_terms_library.json
subtitle_corrector/subtitle_corrector.c
subtitle_corrector/subtitle_corrector.cp312-win_amd64.pyd
subtitle_corrector-0.1.8.dist-info/METADATA
subtitle_corrector-0.1.8.dist-info/WHEEL
subtitle_corrector-0.1.8.dist-info/top_level.txt
subtitle_corrector-0.1.8.dist-info/RECORD
